lab_converter/__init__.py
lab_converter/hex.py
lab_converter/lab2xyz/__init__.py
lab_converter/lab2xyz/read_conversion_csv.py
lab_converter/lab2xyz/rgb_value_checker.py
lab_converter/lab2xyz/xyz.py
lab_converter/rgb.py
lab_converter-0.1.4.dist-info/LICENSE
lab_converter-0.1.4.dist-info/METADATA
lab_converter-0.1.4.dist-info/WHEEL
lab_converter-0.1.4.dist-info/RECORD
