Metadata-Version: 2.1
Name: lab-converter
Version: 0.1.4
Summary: This package contains modules that convert values in the LAB colorspace to values in different colorspaces, such as RGB and XYZ, and different color codes such as hexidecimal. 
Author: Justin Cohen
Author-email: jcohen@curtispackaging.com
Requires-Python: >=3.10,<3.13
Classifier: Programming Language :: Python :: 3
Classifier: Programming Language :: Python :: 3.10
Classifier: Programming Language :: Python :: 3.11
Requires-Dist: colormath (>=3.0.0,<4.0.0)
Requires-Dist: pandas (>=2.1.1,<3.0.0)
Requires-Dist: pytest (>=7.4.2,<8.0.0)
Requires-Dist: pytest-cov (>=4.1.0,<5.0.0)
